{
    "nodeOptions": {
        "customTags": {
            "session": [],
            "message": [],
            "user": []
        },
        "transitionType": "auto",
        "isRetriesExceeded": false,
        "promptOptions": "prompt",
        "reuseMarkedupPhrases": false,
        "interruptOptions": {
            "priority": "task"
        },
        "transitionMode": "initiateCurrentTask",
        "inputHandlingOptions": "useAsEntityValue",
        "reuseOptions": "1",
        "userInputCorrection": true,
        "noAutoCorrection": false,
        "notForReuse": false,
        "contextTags": [],
        "precedence": "entityOverIntent",
        "message": [],
        "errorMessage": [],
        "eventOptions": {
            "maxRetry": {
                "action": "invokeCallTerminationHandler",
                "ref": "AnythingElseDialog"
            }
        },
        "errorPromptSequencing": false
    },
    "vNameSpace": [],
    "preConditions": [],
    "useTaskLevelNs": true,
    "nodeId": "entity65",
    "type": "entity",
    "transitions": [
        {
            "if": {
                "conjoin": "or",
                "tests": [
                    {
                        "context": "ambiguousEntityValues.AccountType",
                        "op": "",
                        "value": ""
                    },
                    {
                        "context": "entities.AccountType.length",
                        "op": "gt",
                        "value": "1"
                    }
                ]
            },
            "then": "script108",
            "metadata": {
                "color": "#299d8e",
                "connId": "dummy732"
            }
        },
        {
            "if": {
                "context": "entities.AccountType",
                "op": "dne"
            },
            "then": "entity161",
            "metadata": {
                "color": "#5ea8d3",
                "connId": "dummy4301"
            }
        },
        {
            "default": "logic243",
            "metadata": {
                "color": "#299d8e",
                "connId": "dummy343"
            }
        }
    ],
    "metadata": {
        "left": 763,
        "top": 2367
    },
    "componentId": "dc-7a2d2f8f-b44d-5eab-959d-daa73a874229"
}