{"nodeOptions":{"customTags":{"session":[],"message":[],"user":[]},"transitionType":"auto","isRetriesExceeded":false,"promptOptions":"required","reuseMarkedupPhrases":false,"interruptOptions":{"priority":"task"},"transitionMode":"initiateCurrentTask","inputHandlingOptions":"useAsEntityValue","reuseOptions":"1","userInputCorrection":true,"noAutoCorrection":false,"notForReuse":false,"contextTags":[],"message":[],"errorMessage":[]},"vNameSpace":[],"preConditions":[],"useTaskLevelNs":true,"nodeId":"message186","type":"message","componentId":"dc-f660f358-6ed6-5111-b43a-5f9c066e481c","transitions":[{"default":"end","metadata":{"color":"#299d8e","connId":"dummy7753"}}],"metadata":{"left":2079,"top":352}}